my_project/__init__.py
my_project/_version.py
my_project/something.py
my_project_andre-0.1.1.dist-info/LICENSE
my_project_andre-0.1.1.dist-info/METADATA
my_project_andre-0.1.1.dist-info/WHEEL
my_project_andre-0.1.1.dist-info/top_level.txt
my_project_andre-0.1.1.dist-info/RECORD
