Metadata-Version: 2.1
Name: my-project-andre
Version: 0.1.1
Summary: Example boilerplate for a simple Python project
Home-page: https://github.com/AndreFCruz/python-proj-boilerplate
Author: AndreFCruz
License: GPL
Keywords: boilerplate
Classifier: Development Status :: 1 - Planning
Classifier: License :: OSI Approved :: GNU General Public License v3 (GPLv3)
Classifier: Programming Language :: Python :: 3
Requires-Python: >=3.8
License-File: LICENSE
Requires-Dist: numpy
